{
    "uid": "d778f9a5-624d-480c-93b1-7fa65810be8b",
    "name": "33_Xgboost",
    "preprocessing": [
        {
            "remove_columns": [
                "building_type_Marina",
                "building_type_Library",
                "building_type_1",
                "roof_shape_1",
                "mwfrs_WallXbracingMomentFrame",
                "mwfrs_1",
                "foundation_type_1",
                "wall_structure_ConcretepiersinsulatedconcreteformICFwalls",
                "wall_structure_1",
                "wall_substrate_Woodsheathing",
                "wall_substrate_1",
                "wall_cladding_VinylSidingstandardStone",
                "wall_cladding_WoodBoardsWoodShakeShinglestonewall",
                "wall_cladding_VinylSidingstandardWoodBoards",
                "wall_cladding_PlywoodSidingStone",
                "wall_cladding_AluminumsidingEIFS",
                "wall_cladding_WoodBoardsstone",
                "wall_cladding_BrickFiberCementBoardPlywoodSiding",
                "wall_cladding_BrickPlywoodSidingVinylSidingunknown",
                "wall_cladding_BrickEIFS",
                "wall_cladding_1",
                "roof_system_SteelcoldformedSteeljoists",
                "roof_system_SteelhotrolledSteeljoists",
                "roof_system_WoodtrussesWoodrafter",
                "roof_system_1",
                "roof_substrate_type_Plywood",
                "roof_substrate_type_1",
                "roof_cover_Metalcorrugatedconcretetopping",
                "roof_cover_BuiltupwithGravel",
                "roof_cover_1"
            ],
            "scale_y": {
                "scale": [
                    0.4351173793654718
                ],
                "mean": [
                    1.068343117970351
                ],
                "var": [
                    0.1893271338258759
                ],
                "n_samples_seen": 470,
                "n_features_in": 1,
                "columns": [
                    "target"
                ],
                "scale_method": "scale_log_and_normal",
                "X_min_values": [
                    0.0
                ]
            },
            "ml_task": "regression",
            "params": {
                "columns_preprocessing": {
                    "building_type_Marina": [
                        "remove_column"
                    ],
                    "building_type_Library": [
                        "remove_column"
                    ],
                    "building_type_1": [
                        "remove_column"
                    ],
                    "roof_shape_1": [
                        "remove_column"
                    ],
                    "mwfrs_WallXbracingMomentFrame": [
                        "remove_column"
                    ],
                    "mwfrs_1": [
                        "remove_column"
                    ],
                    "foundation_type_1": [
                        "remove_column"
                    ],
                    "wall_structure_ConcretepiersinsulatedconcreteformICFwalls": [
                        "remove_column"
                    ],
                    "wall_structure_1": [
                        "remove_column"
                    ],
                    "wall_substrate_Woodsheathing": [
                        "remove_column"
                    ],
                    "wall_substrate_1": [
                        "remove_column"
                    ],
                    "wall_cladding_VinylSidingstandardStone": [
                        "remove_column"
                    ],
                    "wall_cladding_WoodBoardsWoodShakeShinglestonewall": [
                        "remove_column"
                    ],
                    "wall_cladding_VinylSidingstandardWoodBoards": [
                        "remove_column"
                    ],
                    "wall_cladding_PlywoodSidingStone": [
                        "remove_column"
                    ],
                    "wall_cladding_AluminumsidingEIFS": [
                        "remove_column"
                    ],
                    "wall_cladding_WoodBoardsstone": [
                        "remove_column"
                    ],
                    "wall_cladding_BrickFiberCementBoardPlywoodSiding": [
                        "remove_column"
                    ],
                    "wall_cladding_BrickPlywoodSidingVinylSidingunknown": [
                        "remove_column"
                    ],
                    "wall_cladding_BrickEIFS": [
                        "remove_column"
                    ],
                    "wall_cladding_1": [
                        "remove_column"
                    ],
                    "roof_system_SteelcoldformedSteeljoists": [
                        "remove_column"
                    ],
                    "roof_system_SteelhotrolledSteeljoists": [
                        "remove_column"
                    ],
                    "roof_system_WoodtrussesWoodrafter": [
                        "remove_column"
                    ],
                    "roof_system_1": [
                        "remove_column"
                    ],
                    "roof_substrate_type_Plywood": [
                        "remove_column"
                    ],
                    "roof_substrate_type_1": [
                        "remove_column"
                    ],
                    "roof_cover_Metalcorrugatedconcretetopping": [
                        "remove_column"
                    ],
                    "roof_cover_BuiltupwithGravel": [
                        "remove_column"
                    ],
                    "roof_cover_1": [
                        "remove_column"
                    ]
                },
                "target_preprocessing": [
                    "na_exclude",
                    "scale_log_and_normal"
                ],
                "ml_task": "regression"
            }
        },
        {
            "remove_columns": [
                "building_type_Marina",
                "building_type_Library",
                "building_type_1",
                "roof_shape_1",
                "mwfrs_WallXbracingMomentFrame",
                "mwfrs_1",
                "foundation_type_1",
                "wall_structure_ConcretepiersinsulatedconcreteformICFwalls",
                "wall_structure_1",
                "wall_substrate_Woodsheathing",
                "wall_substrate_1",
                "wall_cladding_VinylSidingstandardStone",
                "wall_cladding_WoodBoardsWoodShakeShinglestonewall",
                "wall_cladding_VinylSidingstandardWoodBoards",
                "wall_cladding_PlywoodSidingStone",
                "wall_cladding_AluminumsidingEIFS",
                "wall_cladding_WoodBoardsstone",
                "wall_cladding_BrickFiberCementBoardPlywoodSiding",
                "wall_cladding_BrickPlywoodSidingVinylSidingunknown",
                "wall_cladding_BrickEIFS",
                "wall_cladding_1",
                "roof_system_SteelcoldformedSteeljoists",
                "roof_system_SteelhotrolledSteeljoists",
                "roof_system_WoodtrussesWoodrafter",
                "roof_system_1",
                "roof_substrate_type_Plywood",
                "roof_substrate_type_1",
                "roof_cover_Metalcorrugatedconcretetopping",
                "roof_cover_BuiltupwithGravel",
                "roof_cover_1"
            ],
            "scale_y": {
                "scale": [
                    0.43357573756607504
                ],
                "mean": [
                    1.0679551997644063
                ],
                "var": [
                    0.18798792020596597
                ],
                "n_samples_seen": 470,
                "n_features_in": 1,
                "columns": [
                    "target"
                ],
                "scale_method": "scale_log_and_normal",
                "X_min_values": [
                    0.0
                ]
            },
            "ml_task": "regression",
            "params": {
                "columns_preprocessing": {
                    "building_type_Marina": [
                        "remove_column"
                    ],
                    "building_type_Library": [
                        "remove_column"
                    ],
                    "building_type_1": [
                        "remove_column"
                    ],
                    "roof_shape_1": [
                        "remove_column"
                    ],
                    "mwfrs_WallXbracingMomentFrame": [
                        "remove_column"
                    ],
                    "mwfrs_1": [
                        "remove_column"
                    ],
                    "foundation_type_1": [
                        "remove_column"
                    ],
                    "wall_structure_ConcretepiersinsulatedconcreteformICFwalls": [
                        "remove_column"
                    ],
                    "wall_structure_1": [
                        "remove_column"
                    ],
                    "wall_substrate_Woodsheathing": [
                        "remove_column"
                    ],
                    "wall_substrate_1": [
                        "remove_column"
                    ],
                    "wall_cladding_VinylSidingstandardStone": [
                        "remove_column"
                    ],
                    "wall_cladding_WoodBoardsWoodShakeShinglestonewall": [
                        "remove_column"
                    ],
                    "wall_cladding_VinylSidingstandardWoodBoards": [
                        "remove_column"
                    ],
                    "wall_cladding_PlywoodSidingStone": [
                        "remove_column"
                    ],
                    "wall_cladding_AluminumsidingEIFS": [
                        "remove_column"
                    ],
                    "wall_cladding_WoodBoardsstone": [
                        "remove_column"
                    ],
                    "wall_cladding_BrickFiberCementBoardPlywoodSiding": [
                        "remove_column"
                    ],
                    "wall_cladding_BrickPlywoodSidingVinylSidingunknown": [
                        "remove_column"
                    ],
                    "wall_cladding_BrickEIFS": [
                        "remove_column"
                    ],
                    "wall_cladding_1": [
                        "remove_column"
                    ],
                    "roof_system_SteelcoldformedSteeljoists": [
                        "remove_column"
                    ],
                    "roof_system_SteelhotrolledSteeljoists": [
                        "remove_column"
                    ],
                    "roof_system_WoodtrussesWoodrafter": [
                        "remove_column"
                    ],
                    "roof_system_1": [
                        "remove_column"
                    ],
                    "roof_substrate_type_Plywood": [
                        "remove_column"
                    ],
                    "roof_substrate_type_1": [
                        "remove_column"
                    ],
                    "roof_cover_Metalcorrugatedconcretetopping": [
                        "remove_column"
                    ],
                    "roof_cover_BuiltupwithGravel": [
                        "remove_column"
                    ],
                    "roof_cover_1": [
                        "remove_column"
                    ]
                },
                "target_preprocessing": [
                    "na_exclude",
                    "scale_log_and_normal"
                ],
                "ml_task": "regression"
            }
        },
        {
            "remove_columns": [
                "building_type_Marina",
                "building_type_Library",
                "building_type_1",
                "roof_shape_1",
                "mwfrs_WallXbracingMomentFrame",
                "mwfrs_1",
                "foundation_type_1",
                "wall_structure_ConcretepiersinsulatedconcreteformICFwalls",
                "wall_structure_1",
                "wall_substrate_Woodsheathing",
                "wall_substrate_1",
                "wall_cladding_VinylSidingstandardStone",
                "wall_cladding_WoodBoardsWoodShakeShinglestonewall",
                "wall_cladding_VinylSidingstandardWoodBoards",
                "wall_cladding_PlywoodSidingStone",
                "wall_cladding_AluminumsidingEIFS",
                "wall_cladding_WoodBoardsstone",
                "wall_cladding_BrickFiberCementBoardPlywoodSiding",
                "wall_cladding_BrickPlywoodSidingVinylSidingunknown",
                "wall_cladding_BrickEIFS",
                "wall_cladding_1",
                "roof_system_SteelcoldformedSteeljoists",
                "roof_system_SteelhotrolledSteeljoists",
                "roof_system_WoodtrussesWoodrafter",
                "roof_system_1",
                "roof_substrate_type_Plywood",
                "roof_substrate_type_1",
                "roof_cover_Metalcorrugatedconcretetopping",
                "roof_cover_BuiltupwithGravel",
                "roof_cover_1"
            ],
            "scale_y": {
                "scale": [
                    0.4315714022946746
                ],
                "mean": [
                    1.0495993770942396
                ],
                "var": [
                    0.18625387527859188
                ],
                "n_samples_seen": 470,
                "n_features_in": 1,
                "columns": [
                    "target"
                ],
                "scale_method": "scale_log_and_normal",
                "X_min_values": [
                    0.0
                ]
            },
            "ml_task": "regression",
            "params": {
                "columns_preprocessing": {
                    "building_type_Marina": [
                        "remove_column"
                    ],
                    "building_type_Library": [
                        "remove_column"
                    ],
                    "building_type_1": [
                        "remove_column"
                    ],
                    "roof_shape_1": [
                        "remove_column"
                    ],
                    "mwfrs_WallXbracingMomentFrame": [
                        "remove_column"
                    ],
                    "mwfrs_1": [
                        "remove_column"
                    ],
                    "foundation_type_1": [
                        "remove_column"
                    ],
                    "wall_structure_ConcretepiersinsulatedconcreteformICFwalls": [
                        "remove_column"
                    ],
                    "wall_structure_1": [
                        "remove_column"
                    ],
                    "wall_substrate_Woodsheathing": [
                        "remove_column"
                    ],
                    "wall_substrate_1": [
                        "remove_column"
                    ],
                    "wall_cladding_VinylSidingstandardStone": [
                        "remove_column"
                    ],
                    "wall_cladding_WoodBoardsWoodShakeShinglestonewall": [
                        "remove_column"
                    ],
                    "wall_cladding_VinylSidingstandardWoodBoards": [
                        "remove_column"
                    ],
                    "wall_cladding_PlywoodSidingStone": [
                        "remove_column"
                    ],
                    "wall_cladding_AluminumsidingEIFS": [
                        "remove_column"
                    ],
                    "wall_cladding_WoodBoardsstone": [
                        "remove_column"
                    ],
                    "wall_cladding_BrickFiberCementBoardPlywoodSiding": [
                        "remove_column"
                    ],
                    "wall_cladding_BrickPlywoodSidingVinylSidingunknown": [
                        "remove_column"
                    ],
                    "wall_cladding_BrickEIFS": [
                        "remove_column"
                    ],
                    "wall_cladding_1": [
                        "remove_column"
                    ],
                    "roof_system_SteelcoldformedSteeljoists": [
                        "remove_column"
                    ],
                    "roof_system_SteelhotrolledSteeljoists": [
                        "remove_column"
                    ],
                    "roof_system_WoodtrussesWoodrafter": [
                        "remove_column"
                    ],
                    "roof_system_1": [
                        "remove_column"
                    ],
                    "roof_substrate_type_Plywood": [
                        "remove_column"
                    ],
                    "roof_substrate_type_1": [
                        "remove_column"
                    ],
                    "roof_cover_Metalcorrugatedconcretetopping": [
                        "remove_column"
                    ],
                    "roof_cover_BuiltupwithGravel": [
                        "remove_column"
                    ],
                    "roof_cover_1": [
                        "remove_column"
                    ]
                },
                "target_preprocessing": [
                    "na_exclude",
                    "scale_log_and_normal"
                ],
                "ml_task": "regression"
            }
        },
        {
            "remove_columns": [
                "building_type_Marina",
                "building_type_Library",
                "building_type_1",
                "roof_shape_1",
                "mwfrs_WallXbracingMomentFrame",
                "mwfrs_1",
                "foundation_type_1",
                "wall_structure_ConcretepiersinsulatedconcreteformICFwalls",
                "wall_structure_1",
                "wall_substrate_Woodsheathing",
                "wall_substrate_1",
                "wall_cladding_VinylSidingstandardStone",
                "wall_cladding_WoodBoardsWoodShakeShinglestonewall",
                "wall_cladding_VinylSidingstandardWoodBoards",
                "wall_cladding_PlywoodSidingStone",
                "wall_cladding_AluminumsidingEIFS",
                "wall_cladding_WoodBoardsstone",
                "wall_cladding_BrickFiberCementBoardPlywoodSiding",
                "wall_cladding_BrickPlywoodSidingVinylSidingunknown",
                "wall_cladding_BrickEIFS",
                "wall_cladding_1",
                "roof_system_SteelcoldformedSteeljoists",
                "roof_system_SteelhotrolledSteeljoists",
                "roof_system_WoodtrussesWoodrafter",
                "roof_system_1",
                "roof_substrate_type_Plywood",
                "roof_substrate_type_1",
                "roof_cover_Metalcorrugatedconcretetopping",
                "roof_cover_BuiltupwithGravel",
                "roof_cover_1"
            ],
            "scale_y": {
                "scale": [
                    0.4290683907200567
                ],
                "mean": [
                    1.064930021969803
                ],
                "var": [
                    0.18409968391509926
                ],
                "n_samples_seen": 471,
                "n_features_in": 1,
                "columns": [
                    "target"
                ],
                "scale_method": "scale_log_and_normal",
                "X_min_values": [
                    0.0
                ]
            },
            "ml_task": "regression",
            "params": {
                "columns_preprocessing": {
                    "building_type_Marina": [
                        "remove_column"
                    ],
                    "building_type_Library": [
                        "remove_column"
                    ],
                    "building_type_1": [
                        "remove_column"
                    ],
                    "roof_shape_1": [
                        "remove_column"
                    ],
                    "mwfrs_WallXbracingMomentFrame": [
                        "remove_column"
                    ],
                    "mwfrs_1": [
                        "remove_column"
                    ],
                    "foundation_type_1": [
                        "remove_column"
                    ],
                    "wall_structure_ConcretepiersinsulatedconcreteformICFwalls": [
                        "remove_column"
                    ],
                    "wall_structure_1": [
                        "remove_column"
                    ],
                    "wall_substrate_Woodsheathing": [
                        "remove_column"
                    ],
                    "wall_substrate_1": [
                        "remove_column"
                    ],
                    "wall_cladding_VinylSidingstandardStone": [
                        "remove_column"
                    ],
                    "wall_cladding_WoodBoardsWoodShakeShinglestonewall": [
                        "remove_column"
                    ],
                    "wall_cladding_VinylSidingstandardWoodBoards": [
                        "remove_column"
                    ],
                    "wall_cladding_PlywoodSidingStone": [
                        "remove_column"
                    ],
                    "wall_cladding_AluminumsidingEIFS": [
                        "remove_column"
                    ],
                    "wall_cladding_WoodBoardsstone": [
                        "remove_column"
                    ],
                    "wall_cladding_BrickFiberCementBoardPlywoodSiding": [
                        "remove_column"
                    ],
                    "wall_cladding_BrickPlywoodSidingVinylSidingunknown": [
                        "remove_column"
                    ],
                    "wall_cladding_BrickEIFS": [
                        "remove_column"
                    ],
                    "wall_cladding_1": [
                        "remove_column"
                    ],
                    "roof_system_SteelcoldformedSteeljoists": [
                        "remove_column"
                    ],
                    "roof_system_SteelhotrolledSteeljoists": [
                        "remove_column"
                    ],
                    "roof_system_WoodtrussesWoodrafter": [
                        "remove_column"
                    ],
                    "roof_system_1": [
                        "remove_column"
                    ],
                    "roof_substrate_type_Plywood": [
                        "remove_column"
                    ],
                    "roof_substrate_type_1": [
                        "remove_column"
                    ],
                    "roof_cover_Metalcorrugatedconcretetopping": [
                        "remove_column"
                    ],
                    "roof_cover_BuiltupwithGravel": [
                        "remove_column"
                    ],
                    "roof_cover_1": [
                        "remove_column"
                    ]
                },
                "target_preprocessing": [
                    "na_exclude",
                    "scale_log_and_normal"
                ],
                "ml_task": "regression"
            }
        },
        {
            "remove_columns": [
                "building_type_Marina",
                "building_type_Library",
                "building_type_1",
                "roof_shape_1",
                "mwfrs_WallXbracingMomentFrame",
                "mwfrs_1",
                "foundation_type_1",
                "wall_structure_ConcretepiersinsulatedconcreteformICFwalls",
                "wall_structure_1",
                "wall_substrate_Woodsheathing",
                "wall_substrate_1",
                "wall_cladding_VinylSidingstandardStone",
                "wall_cladding_WoodBoardsWoodShakeShinglestonewall",
                "wall_cladding_VinylSidingstandardWoodBoards",
                "wall_cladding_PlywoodSidingStone",
                "wall_cladding_AluminumsidingEIFS",
                "wall_cladding_WoodBoardsstone",
                "wall_cladding_BrickFiberCementBoardPlywoodSiding",
                "wall_cladding_BrickPlywoodSidingVinylSidingunknown",
                "wall_cladding_BrickEIFS",
                "wall_cladding_1",
                "roof_system_SteelcoldformedSteeljoists",
                "roof_system_SteelhotrolledSteeljoists",
                "roof_system_WoodtrussesWoodrafter",
                "roof_system_1",
                "roof_substrate_type_Plywood",
                "roof_substrate_type_1",
                "roof_cover_Metalcorrugatedconcretetopping",
                "roof_cover_BuiltupwithGravel",
                "roof_cover_1"
            ],
            "scale_y": {
                "scale": [
                    0.4306161692304617
                ],
                "mean": [
                    1.056761265102944
                ],
                "var": [
                    0.18543028520271765
                ],
                "n_samples_seen": 471,
                "n_features_in": 1,
                "columns": [
                    "target"
                ],
                "scale_method": "scale_log_and_normal",
                "X_min_values": [
                    0.0
                ]
            },
            "ml_task": "regression",
            "params": {
                "columns_preprocessing": {
                    "building_type_Marina": [
                        "remove_column"
                    ],
                    "building_type_Library": [
                        "remove_column"
                    ],
                    "building_type_1": [
                        "remove_column"
                    ],
                    "roof_shape_1": [
                        "remove_column"
                    ],
                    "mwfrs_WallXbracingMomentFrame": [
                        "remove_column"
                    ],
                    "mwfrs_1": [
                        "remove_column"
                    ],
                    "foundation_type_1": [
                        "remove_column"
                    ],
                    "wall_structure_ConcretepiersinsulatedconcreteformICFwalls": [
                        "remove_column"
                    ],
                    "wall_structure_1": [
                        "remove_column"
                    ],
                    "wall_substrate_Woodsheathing": [
                        "remove_column"
                    ],
                    "wall_substrate_1": [
                        "remove_column"
                    ],
                    "wall_cladding_VinylSidingstandardStone": [
                        "remove_column"
                    ],
                    "wall_cladding_WoodBoardsWoodShakeShinglestonewall": [
                        "remove_column"
                    ],
                    "wall_cladding_VinylSidingstandardWoodBoards": [
                        "remove_column"
                    ],
                    "wall_cladding_PlywoodSidingStone": [
                        "remove_column"
                    ],
                    "wall_cladding_AluminumsidingEIFS": [
                        "remove_column"
                    ],
                    "wall_cladding_WoodBoardsstone": [
                        "remove_column"
                    ],
                    "wall_cladding_BrickFiberCementBoardPlywoodSiding": [
                        "remove_column"
                    ],
                    "wall_cladding_BrickPlywoodSidingVinylSidingunknown": [
                        "remove_column"
                    ],
                    "wall_cladding_BrickEIFS": [
                        "remove_column"
                    ],
                    "wall_cladding_1": [
                        "remove_column"
                    ],
                    "roof_system_SteelcoldformedSteeljoists": [
                        "remove_column"
                    ],
                    "roof_system_SteelhotrolledSteeljoists": [
                        "remove_column"
                    ],
                    "roof_system_WoodtrussesWoodrafter": [
                        "remove_column"
                    ],
                    "roof_system_1": [
                        "remove_column"
                    ],
                    "roof_substrate_type_Plywood": [
                        "remove_column"
                    ],
                    "roof_substrate_type_1": [
                        "remove_column"
                    ],
                    "roof_cover_Metalcorrugatedconcretetopping": [
                        "remove_column"
                    ],
                    "roof_cover_BuiltupwithGravel": [
                        "remove_column"
                    ],
                    "roof_cover_1": [
                        "remove_column"
                    ]
                },
                "target_preprocessing": [
                    "na_exclude",
                    "scale_log_and_normal"
                ],
                "ml_task": "regression"
            }
        }
    ],
    "learners": [
        {
            "library_version": "1.5.1",
            "algorithm_name": "Extreme Gradient Boosting",
            "algorithm_short_name": "Xgboost",
            "uid": "ab72e4fa-e4e9-4037-b719-acdabf1ed98e",
            "params": {
                "model_type": "Xgboost",
                "ml_task": "regression",
                "n_jobs": -1,
                "seed": 1235,
                "objective": "reg:squarederror",
                "eta": 0.075,
                "max_depth": 8,
                "min_child_weight": 5,
                "subsample": 0.9,
                "colsample_bytree": 1.0,
                "eval_metric": "rmse",
                "explain_level": 1
            },
            "name": "learner_fold_0",
            "best_ntree_limit": 32
        },
        {
            "library_version": "1.5.1",
            "algorithm_name": "Extreme Gradient Boosting",
            "algorithm_short_name": "Xgboost",
            "uid": "39997005-bc5c-4525-aa15-c18deed1d0e8",
            "params": {
                "model_type": "Xgboost",
                "ml_task": "regression",
                "n_jobs": -1,
                "seed": 1235,
                "objective": "reg:squarederror",
                "eta": 0.075,
                "max_depth": 8,
                "min_child_weight": 5,
                "subsample": 0.9,
                "colsample_bytree": 1.0,
                "eval_metric": "rmse",
                "explain_level": 1
            },
            "name": "learner_fold_1",
            "best_ntree_limit": 40
        },
        {
            "library_version": "1.5.1",
            "algorithm_name": "Extreme Gradient Boosting",
            "algorithm_short_name": "Xgboost",
            "uid": "4e6a3f51-6ff1-452f-926d-0698499e9e1d",
            "params": {
                "model_type": "Xgboost",
                "ml_task": "regression",
                "n_jobs": -1,
                "seed": 1235,
                "objective": "reg:squarederror",
                "eta": 0.075,
                "max_depth": 8,
                "min_child_weight": 5,
                "subsample": 0.9,
                "colsample_bytree": 1.0,
                "eval_metric": "rmse",
                "explain_level": 1
            },
            "name": "learner_fold_2",
            "best_ntree_limit": 34
        },
        {
            "library_version": "1.5.1",
            "algorithm_name": "Extreme Gradient Boosting",
            "algorithm_short_name": "Xgboost",
            "uid": "1aeea5c4-59aa-4306-914d-9861bc59bfc6",
            "params": {
                "model_type": "Xgboost",
                "ml_task": "regression",
                "n_jobs": -1,
                "seed": 1235,
                "objective": "reg:squarederror",
                "eta": 0.075,
                "max_depth": 8,
                "min_child_weight": 5,
                "subsample": 0.9,
                "colsample_bytree": 1.0,
                "eval_metric": "rmse",
                "explain_level": 1
            },
            "name": "learner_fold_3",
            "best_ntree_limit": 137
        },
        {
            "library_version": "1.5.1",
            "algorithm_name": "Extreme Gradient Boosting",
            "algorithm_short_name": "Xgboost",
            "uid": "69146d2a-209e-43ba-9454-351df73f79f3",
            "params": {
                "model_type": "Xgboost",
                "ml_task": "regression",
                "n_jobs": -1,
                "seed": 1235,
                "objective": "reg:squarederror",
                "eta": 0.075,
                "max_depth": 8,
                "min_child_weight": 5,
                "subsample": 0.9,
                "colsample_bytree": 1.0,
                "eval_metric": "rmse",
                "explain_level": 1
            },
            "name": "learner_fold_4",
            "best_ntree_limit": 44
        }
    ],
    "params": {
        "additional": {
            "max_rounds": 10000,
            "early_stopping_rounds": 50,
            "max_rows_limit": null,
            "max_cols_limit": null
        },
        "preprocessing": {
            "columns_preprocessing": {
                "building_type_Marina": [
                    "remove_column"
                ],
                "building_type_Library": [
                    "remove_column"
                ],
                "building_type_1": [
                    "remove_column"
                ],
                "roof_shape_1": [
                    "remove_column"
                ],
                "mwfrs_WallXbracingMomentFrame": [
                    "remove_column"
                ],
                "mwfrs_1": [
                    "remove_column"
                ],
                "foundation_type_1": [
                    "remove_column"
                ],
                "wall_structure_ConcretepiersinsulatedconcreteformICFwalls": [
                    "remove_column"
                ],
                "wall_structure_1": [
                    "remove_column"
                ],
                "wall_substrate_Woodsheathing": [
                    "remove_column"
                ],
                "wall_substrate_1": [
                    "remove_column"
                ],
                "wall_cladding_VinylSidingstandardStone": [
                    "remove_column"
                ],
                "wall_cladding_WoodBoardsWoodShakeShinglestonewall": [
                    "remove_column"
                ],
                "wall_cladding_VinylSidingstandardWoodBoards": [
                    "remove_column"
                ],
                "wall_cladding_PlywoodSidingStone": [
                    "remove_column"
                ],
                "wall_cladding_AluminumsidingEIFS": [
                    "remove_column"
                ],
                "wall_cladding_WoodBoardsstone": [
                    "remove_column"
                ],
                "wall_cladding_BrickFiberCementBoardPlywoodSiding": [
                    "remove_column"
                ],
                "wall_cladding_BrickPlywoodSidingVinylSidingunknown": [
                    "remove_column"
                ],
                "wall_cladding_BrickEIFS": [
                    "remove_column"
                ],
                "wall_cladding_1": [
                    "remove_column"
                ],
                "roof_system_SteelcoldformedSteeljoists": [
                    "remove_column"
                ],
                "roof_system_SteelhotrolledSteeljoists": [
                    "remove_column"
                ],
                "roof_system_WoodtrussesWoodrafter": [
                    "remove_column"
                ],
                "roof_system_1": [
                    "remove_column"
                ],
                "roof_substrate_type_Plywood": [
                    "remove_column"
                ],
                "roof_substrate_type_1": [
                    "remove_column"
                ],
                "roof_cover_Metalcorrugatedconcretetopping": [
                    "remove_column"
                ],
                "roof_cover_BuiltupwithGravel": [
                    "remove_column"
                ],
                "roof_cover_1": [
                    "remove_column"
                ]
            },
            "target_preprocessing": [
                "na_exclude",
                "scale_log_and_normal"
            ],
            "ml_task": "regression"
        },
        "validation_strategy": {
            "validation_type": "kfold",
            "k_folds": 5,
            "shuffle": true,
            "X_path": "Perform_regression/X.data",
            "y_path": "Perform_regression/y.data",
            "results_path": "Perform_regression"
        },
        "learner": {
            "model_type": "Xgboost",
            "ml_task": "regression",
            "n_jobs": -1,
            "seed": 1235,
            "objective": "reg:squarederror",
            "eta": 0.075,
            "max_depth": 8,
            "min_child_weight": 5,
            "subsample": 0.9,
            "colsample_bytree": 1.0,
            "eval_metric": "rmse",
            "explain_level": 1
        },
        "automl_random_state": 1234,
        "ml_task": "regression",
        "explain_level": 1,
        "name": "33_Xgboost",
        "status": "initialized",
        "final_loss": null,
        "train_time": null,
        "data_type": "original",
        "max_time_for_learner": 72.0
    },
    "saved": [
        "33_Xgboost/learner_fold_0.xgboost",
        "33_Xgboost/learner_fold_1.xgboost",
        "33_Xgboost/learner_fold_2.xgboost",
        "33_Xgboost/learner_fold_3.xgboost",
        "33_Xgboost/learner_fold_4.xgboost"
    ],
    "predictions_fname": "33_Xgboost/predictions_out_of_folds.csv",
    "metric_name": "rmse",
    "final_loss": 0.9165809189669,
    "train_time": 19.56524395942688,
    "is_stacked": false,
    "single_prediction_time": 0.0962681770324707
}